{"status":"success","errors":[],"data":[{"id":"26001","text":"Не умеешь — не лезь, блять!","html":"<span class=\"dash\">Не&nbsp;умеешь&nbsp;—</span><br>не&nbsp;лезь,<br>блять!","tags":["music","life","office","gtd","friendship"],"conclusions":[]},{"id":"7208","text":"Лён факин инглиш!","html":"Лён<br>факин<br>инглиш!","tags":["design","coding","text","frontend","office","kids","translate","travel"],"conclusions":[]},{"id":"6698","text":"Переноси блять сроки с запасом!","html":"Переноси<br>блять<br>сроки<br>с&nbsp;запасом!","tags":["design","coding","markup","text","marketing","education","life","frontend","office","gtd"],"conclusions":[]},{"id":"7918","text":"Говори блять грамотно!","html":"Говори<br>блять<br>грамотно!","tags":["text","marketing","education","life","office","friendship","translate"],"conclusions":[]},{"id":"4277","text":"Печатай блять быстро!","html":"Печатай<br>блять<br>быстро!","tags":["coding","text","education","frontend","office"],"conclusions":[]},{"id":"26214","text":"Делай больше, пизди меньше!","html":"Делай<br>больше,<br>пизди<br>меньше!","tags":["education","life","business","frontend","office","gtd","love","money","friendship"],"conclusions":[]},{"id":"26026","text":"Делай блять больше чем обещаешь!","html":"Делай<br>блять<br>больше<br>чем обещаешь!","tags":["life","for-him","for-her","office","gtd","love","friendship"],"conclusions":[]},{"id":"26257","text":"Люди меняются, ёпта","html":"Люди<br>меняются,<br><span class=\"heighten\">ёпта</span>","tags":["education","life","for-him","for-her","newyear","business","office","love","kids","friendship","health"],"conclusions":[]},{"id":"24088","text":"Говори блять правду!","html":"Говори<br>блять<br>правду!","tags":["for-him","for-her","office","gtd","love","kids","money","friendship"],"conclusions":[]},{"id":"25891","text":"Не стыдись ошибок, ёпта!","html":"Не стыдись<br>ошибок,<br><span class=\"heighten\">ёпта!</span>","tags":["music","tricks","life","for-him","for-her","business","office","kids","friendship"],"conclusions":[]},{"id":"25903","text":"Не подписывай блять не прочитав!","html":"Не&nbsp;подписывай,<br>не&nbsp;прочитав,<br>блять!","tags":["life","business","office","gtd"],"conclusions":[]},{"id":"25926","text":"Найди работу попиздаче!","html":"Найди<br>работу<br>попиздаче!","tags":["life","office","money"],"conclusions":[]},{"id":"25874","text":"Похуй, пусть смеются!","html":"Похуй,<br>пусть<br>смеются!","tags":["life","business","office","gtd","friendship"],"conclusions":[]},{"id":"9117","text":"Хватит думать, блять — делай!","html":"Хватит<br>думать,<br><span class=\"dash\">блять&nbsp;—</span><br><span class=\"heighten\">делай!</span>","tags":["design","coding","music","tricks","business","office","gtd","friendship"],"conclusions":[]},{"id":"37","text":"Иди блять отдохни немного!","html":"Иди<br>блять<br>отдохни<br>немного!","tags":["design","coding","markup","photo","music","medicine","education","life","office","gtd"],"conclusions":[]},{"id":"25986","text":"Работай, блять, и не жди восторгов!","html":"Работай,<br>блять,<br>и не&nbsp;жди<br>восторгов!","tags":["life","business","office","gtd"],"conclusions":[]},{"id":"13448","text":"Заправь блять принтер!","html":"Заправь<br>блять<br>принтер!","tags":["education","life","office"],"conclusions":[]},{"id":"26209","text":"Слушай маму, блять!","html":"Слушай<br>маму,<br>блять!","tags":["life","for-him","for-her","newyear","office","love","kids","friendship"],"conclusions":[]},{"id":"26323","text":"Не охай — всем похуй!","html":"<span class=\"dash\">Не&nbsp;охай&nbsp;—</span><br>всем<br><span class=\"heighten\">похуй!</span>","tags":["design","coding","markup","photo","text","marketing","driving","music","tricks","medicine","education","life","for-him","for-her","business","frontend","office","snowboard","gtd","love","kids","money","friendship","translate","dentist","travel","health"],"conclusions":[]},{"id":"7078","text":"Перестань всё усложнять, ёпта!","html":"Перестань<br><span class=\"heighten\">всё<br>усложнять,<br><span class=\"heighten\">ёпта!</span></span>","tags":["design","coding","markup","text","music","life","business","frontend","office","gtd"],"conclusions":[]},{"id":"26145","text":"Знай, блять, каким ты хочешь стать!","html":"Знай,<br>блять,<br>каким<br>ты<br>хочешь<br>стать!","tags":["education","life","for-him","business","office","friendship"],"conclusions":[]},{"id":"26009","text":"Не пытайся блять изменить невозможное!","html":"Не&nbsp;пытайся<br>блять<br>изменить<br>невозможное!","tags":["life","for-him","for-her","business","office","gtd","love","friendship"],"conclusions":[]},{"id":"26164","text":"Выслушай блять обе стороны!","html":"Выслушай<br>блять<br>обе стороны!","tags":["life","business","office","kids"],"conclusions":[]},{"id":"25922","text":"Работай лучше окружающих, ёпта!","html":"Работай<br>лучше<br>окружающих,<br><span class=\"heighten\">ёпта!</span>","tags":["life","office","gtd","money"],"conclusions":[]},{"id":"26048","text":"Не устраивай ёбаный театр!","html":"Не&nbsp;устраивай<br><span class=\"heighten\">ёбаный<br>театр!</span>","tags":["life","for-him","for-her","office","love","friendship"],"conclusions":[]},{"id":"25998","text":"Не суди блять по внешности!","html":"Не&nbsp;суди<br>блять<br>по&nbsp;внешности!","tags":["life","for-him","for-her","business","office","gtd","love","friendship"],"conclusions":[]},{"id":"25880","text":"Нахуя переживать?","html":"Нахуй так<br>переживать?","tags":["life","business","office","gtd","money","friendship"],"conclusions":[]},{"id":"16577","text":"Не бойся блять своих желаний!","html":"Не&nbsp;бойся<br>блять<br>своих<br>желаний!","tags":["life","office","love","friendship","travel"],"conclusions":[]},{"id":"7138","text":"Не жалуйся блять на нехватку времени!","html":"Не&nbsp;жалуйся<br>блять<br>на&nbsp;нехватку<br>времени!","tags":["design","coding","education","life","newyear","frontend","office","gtd","love","money","friendship","health"],"conclusions":[]},{"id":"26259","text":"Делай всё в срок, блять!","html":"Делай<br><span class=\"heighten\">всё<br>в&nbsp;срок,<br>блять!</span>","tags":["design","coding","markup","life","for-him","newyear","business","frontend","office","gtd","love","money","travel","health"],"conclusions":[]},{"id":"13198","text":"Не пизди блять лишнего!","html":"Не&nbsp;пизди<br>блять<br>лишнего!","tags":["life","office","love"],"conclusions":[]},{"id":"26033","text":"Планируй блять свой день!","html":"Планируй<br>блять<br><span class=\"heighten\">свой<br>день!</span>","tags":["life","business","office","gtd"],"conclusions":[]},{"id":"15737","text":"Предупреждай блять заранее!","html":"Предупреждай<br>блять<br>заранее!","tags":["for-him","for-her","business","office","gtd","love","friendship"],"conclusions":[]},{"id":"478","text":"Не ищи блять отмазок!","html":"Не&nbsp;ищи<br>блять<br>отмазок!","tags":["life","business","office","gtd","love"],"conclusions":[]},{"id":"7238","text":"Наведи блять порядок!","html":"Наведи<br>блять<br>порядок!","tags":["life","business","office","gtd"],"conclusions":[]},{"id":"26063","text":"Упражняй блять мозги!","html":"Упражняй<br>блять<br>мозги!","tags":["life","business","office","gtd","money","health"],"conclusions":[]},{"id":"25854","text":"Не топчись блять на месте!","html":"Не&nbsp;топчись<br>блять<br>на&nbsp;месте!","tags":["life","office","gtd","love","kids","money"],"conclusions":[]},{"id":"127","text":"Постоянно блять развивайся!","html":"Постоянно<br>блять<br>развивайся!","tags":["design","coding","music","medicine","life","business","frontend","office","snowboard"],"conclusions":[]},{"id":"26231","text":"На одыхе, блять, — отдыхай!","html":"На одыхе<br>блять<br>отдыхай!","tags":["life","business","office","gtd","kids","travel"],"conclusions":[]},{"id":"45","text":"Выбирай себе клиентов, ёпта!","html":"Выбирай<br>себе<br>клиентов,<br><span class=\"heighten\">ёпта!</span>","tags":["design","life","business","office","gtd"],"conclusions":[]}]}